tracy
triage
tt_lib
ttnn
