Metadata-Version: 2.1
Name: ttnn
Version: 0.65.1rc12
Summary: General compute framework for Tenstorrent devices
Home-page: http://www.tenstorrent.com
Author: Tenstorrent
Author-email: info@tenstorrent.com
License: Apache-2.0
Project-URL: Homepage, https://docs.tenstorrent.com/tt-metal/latest/ttnn
Project-URL: Documentation, https://docs.tenstorrent.com/tt-metal/latest/ttnn
Project-URL: Repository, https://github.com/tenstorrent/tt-metal
Project-URL: Issues, https://github.com/tenstorrent/tt-metal/issues
Keywords: metalium,ttnn,tt-metal,machine learning,tenstorrent,libnuma,libhwloc
Requires-Python: >=3.10
License-File: LICENSE
License-File: LICENSE_understanding.txt
Requires-Dist: numpy <2,>=1.24.4
Requires-Dist: loguru >=0.6.0
Requires-Dist: networkx >=3.1
Requires-Dist: graphviz >=0.20.3
Requires-Dist: pyyaml >=5.4
Requires-Dist: click >=8.1.7
Requires-Dist: pandas >=2.0.3
Requires-Dist: seaborn >=0.13.2
